ccbsc_api/__init__.py
ccbsc_api/_ccbsc.py
ccbsc_api/classification/__init__.py
ccbsc_api/classification/_classification.py
ccbsc_api/classification/_pollen.py
ccbsc_api/device/__init__.py
ccbsc_api/device/_photo.py
ccbsc_api/example/__init__.py
ccbsc_api/example/_dummy_algorithm.py
ccbsc_api-1.0.0.dist-info/LICENSE
ccbsc_api-1.0.0.dist-info/METADATA
ccbsc_api-1.0.0.dist-info/WHEEL
ccbsc_api-1.0.0.dist-info/top_level.txt
ccbsc_api-1.0.0.dist-info/RECORD
