Metadata-Version: 2.1
Name: ccbsc-api
Version: 1.0.0
Summary: Framework to apply new algorithms on images of pollen.
Home-page: https://github.com/RobertGebauer/pollen-validation-ccbsc
Author: Robert Gebauer
License: MIT
Platform: any
License-File: LICENSE
